pypocketutils/__init__.py
pypocketutils-0.1.2.dist-info/licenses/LICENSE
pypocketutils-0.1.2.dist-info/METADATA
pypocketutils-0.1.2.dist-info/WHEEL
pypocketutils-0.1.2.dist-info/top_level.txt
pypocketutils-0.1.2.dist-info/RECORD
